scHPL/__init__.py
scHPL/evaluate.py
scHPL/faissKNeighbors.py
scHPL/learn.py
scHPL/predict.py
scHPL/train.py
scHPL/update.py
scHPL/utils.py
scHPL-1.0.5.dist-info/LICENSE
scHPL-1.0.5.dist-info/METADATA
scHPL-1.0.5.dist-info/WHEEL
scHPL-1.0.5.dist-info/top_level.txt
scHPL-1.0.5.dist-info/RECORD
