Metadata-Version: 2.1
Name: scHPL
Version: 1.0.5
Summary: Hierarchical progressive learning pipeline for single-cell RNA-sequencing datasets
Home-page: https://github.com/lcmmichielsen/scHPL
Author: Lieke Michielsen
Author-email: l.c.m.michielsen@tudelft.nl
License: MIT
Classifier: Programming Language :: Python :: 3
Classifier: License :: OSI Approved :: MIT License
Classifier: Operating System :: OS Independent
Requires-Python: >=3.6
License-File: LICENSE
Requires-Dist: numpy >=1.19.2
Requires-Dist: scipy >=1.5.2
Requires-Dist: scikit-learn >=0.23.2
Requires-Dist: pandas <2,>=1.1.2
Requires-Dist: newick ~=1.0.0
Requires-Dist: anndata >=0.7.4
Requires-Dist: matplotlib >=3.3.1
Requires-Dist: seaborn >=0.11.1
